eth_contract/__init__.py
eth_contract/common.py
eth_contract/core.py
eth_contract/events.py
eth_contract/exceptions.py
eth_contract/functions.py
eth_contract/utils.py
ethereum_contract-0.1.0.dist-info/DESCRIPTION.rst
ethereum_contract-0.1.0.dist-info/METADATA
ethereum_contract-0.1.0.dist-info/metadata.json
ethereum_contract-0.1.0.dist-info/RECORD
ethereum_contract-0.1.0.dist-info/top_level.txt
ethereum_contract-0.1.0.dist-info/WHEEL
