Metadata-Version: 2.0
Name: ethereum-contract
Version: 0.1.0
Summary: Ethereum Contract
Home-page: https://github.com/pipermerriam/ethereum-contract
Author: Piper Merriam
Author-email: pipermerriam@gmail.com
License: MIT
Keywords: ethereum
Platform: UNKNOWN
Classifier: Development Status :: 2 - Pre-Alpha
Classifier: Intended Audience :: Developers
Classifier: License :: OSI Approved :: BSD License
Classifier: Natural Language :: English
Classifier: Programming Language :: Python :: 2
Classifier: Programming Language :: Python :: 2.7
Classifier: Programming Language :: Python :: 3
Classifier: Programming Language :: Python :: 3.3
Classifier: Programming Language :: Python :: 3.4
Requires-Dist: pysha3 (>=0.3)
Requires-Dist: ethereum-abi-utils (>=0.1.0)
